relaxit/__init__.py
relaxit/_version.py
relaxit/distributions/CorrelatedRelaxedBernoulli.py
relaxit/distributions/DecoupledStraightThroughGumbelSoftmax.py
relaxit/distributions/GaussianRelaxedBernoulli.py
relaxit/distributions/GeneralizedGumbelSoftmax.py
relaxit/distributions/GumbelSoftmaxTopK.py
relaxit/distributions/HardConcrete.py
relaxit/distributions/InvertibleGaussian.py
relaxit/distributions/LogisticNormalSoftmax.py
relaxit/distributions/RebarRelaxation.py
relaxit/distributions/StochasticTimesSmooth.py
relaxit/distributions/StraightThroughBernoulli.py
relaxit/distributions/__init__.py
relaxit/distributions/approx.py
relaxit/distributions/kl.py
relaxit/rl_benchmarks/__init__.py
relaxit/rl_benchmarks/algorithms/__init__.py
relaxit/rl_benchmarks/algorithms/a2c.py
relaxit/rl_benchmarks/algorithms/reinforce.py
relaxit/rl_benchmarks/algorithms/relax.py
relaxit-1.2.1.dist-info/licenses/LICENSE
relaxit-1.2.1.dist-info/METADATA
relaxit-1.2.1.dist-info/WHEEL
relaxit-1.2.1.dist-info/top_level.txt
relaxit-1.2.1.dist-info/RECORD
