Metadata-Version: 2.4
Name: relaxit
Version: 1.2.1
Summary: Relaxit: A Python Library for Optimizing Discrete Probability Distributions in Neural Networks
Author: Daniil Dorin, Igor Ignashin, Nikita Kiselev, Andrey Veprikov, Vladislav Minashkin, Papay Ivan, Meshkov Vlad, Stepanov Ilya
License: MIT
Project-URL: Homepage, https://github.com/intsystems/relaxit
Requires-Python: >=3.9
License-File: LICENSE
Requires-Dist: torch>=2.8.0
Requires-Dist: pyro-ppl>=1.9.1
Dynamic: license-file
